fastapi_filemanager/__init__.py
fastapi_filemanager/exceptions.py
fastapi_filemanager/file_manager.py
fastapifilemanager-1.1.4.dist-info/licenses/LICENSE
fastapifilemanager-1.1.4.dist-info/METADATA
fastapifilemanager-1.1.4.dist-info/WHEEL
fastapifilemanager-1.1.4.dist-info/top_level.txt
fastapifilemanager-1.1.4.dist-info/RECORD
